benjen.py
setup.py
Benjen.egg-info/PKG-INFO
Benjen.egg-info/SOURCES.txt
Benjen.egg-info/dependency_links.txt
Benjen.egg-info/entry_points.txt
Benjen.egg-info/requires.txt
Benjen.egg-info/top_level.txt