Metadata-Version: 1.0
Name: Benjen
Version: 1.1.1
Summary: Static blog engine
Home-page: https://github.com/daeken/benjen
Author: Cody Brocious
Author-email: cody.brocious@gmail.com
License: Public Domain/WTFPL
Keywords: blog static
Platform: UNKNOWN
